Workbook

Sheet CI
F4: COMMERCIAL INVOICE
B5: Consignee : | I5: Invoice No. | M5: Date
B6: J. CARTER SPORTING CLUB LIMITED 1 CENTRAL STREET, MANCHESTER, UNITED KINGDOM,, M2 5WR | I6: 0654/INV/2025 | M6: 45810
I7: Term of Payment | K7: : | L7: LC - 180 DAYS AFTER BILL OF LADING DATE OR AIRWAY BILL DATE
I9: Bank Ref./LC No. | K9: : | L9: IMP750070263
I11: Date of Issue | K11: : | L11: 45225
B12: Notify Party : | I12: Issued by | K12: :
B13: J. CARTER SPORTING CLUB LIMITED 1 CENTRAL STREET, MANCHESTER, UNITED KINGDOM,, M2 5WR | I13: LOYDGB2LDIO
I17: HBL / HAWB No. | K17: :
I18: Shipped on Board Date | K18: :
B19: Port of Loading : | F19: Port of Discharge : | I19: PO NO
B20: SOEKARNO HATTA, JAKARTA AIRPORT, INDONESIA | F20: AMSTERDAM, NL | I20: EPO12508755, EPO12508757, WPO12508771, WPO12508772
F21: Port of Delivery :
F22: AMSTERDAM, NL
B23: Ship Mode | D23: : | E23: AIR
B24: BOOKING NO | D24: : | E24: CA25000660
B28: Description of Goods | L28: Quantity | M28: Unit Price | N28: Amount
L29: PIECES | M29: USD | N29: FCA
B32: 116 CARTONS = 3,711 PIECES OF APPAREL GOODS
B33: CONSIST OF :
B35: 52 CARTONS = 1,758 PIECES OF APPAREL GOODS
B36: PO NO. : EPO12508755
B37: ORDER LINE | C37: STYLE NO | E37: DESCRIPTION | J37: HS CODE
B38: 001 | C38: TI12081-010 | E38: FC UTRECHT PERFORMANCE KNIT SUIT | J38: 61109000 | L38: 100 | M38: 15.28 | N38: =M38*L38 -> 1528
B39: 003 | C39: TJ12049-010 | E39: FC UTRECHT PERFORMANCE KNIT SHORT- PKTS | J39: 61034900 | L39: 100 | M39: 6.74 | N39: =L39*M39 -> 674
B40: 004 | C40: TJ12050-010 | E40: FC UTRECHT PERFORMANCE MIDLAYER TOP | J40: 61109000 | L40: 150 | M40: 11.08 | N40: =L40*M40 -> 1662
B41: 005 | C41: TJ12052-010 | E41: FC UTRECHT PERFORMANCE KNIT PANT- PKTS | J41: 61034900 | L41: 100 | M41: 11.92 | N41: =L41*M41 -> 1192
B42: 007 | C42: TM12049-010 | E42: FC UTRECHT PERFORMANCE KNIT SHORT- PKTS | J42: 61034900 | L42: 206 | M42: 7.52 | N42: =L42*M42 -> 1549.12
B43: 008 | C43: TM12050-010 | E43: FC UTRECHT PERFORMANCE MIDLAYER TOP | J43: 61109000 | L43: 300 | M43: 12.33 | N43: =L43*M43 -> 3699
B44: 009 | C44: TM12052-010 | E44: FC UTRECHT PERFORMANCE KNIT PANT- PKTS | J44: 61034900 | L44: 202 | M44: 13.27 | N44: =L44*M44 -> 2680.54
B45: 002 | C45: TJ12046-072 | E45: FC UTRECHT PERFORMANCE SHORT SLEEVE TEE | J45: 61099020 | L45: 200 | M45: 4.87 | N45: =L45*M45 -> 974
B46: 006 | C46: TM12046-072 | E46: FC UTRECHT PERFORMANCE SHORT SLEEVE TEE | J46: 61099020 | L46: 400 | M46: 5.44 | N46: =L46*M46 -> 2176
B48: SUB TOTAL | L48: =SUM(L38:L46) -> 1758 | N48: =SUM(N38:N46) -> 16134.66
B50: 35 CARTONS = 1200 PIECES OF APPAREL GOODS
B51: PO NO. : WPO12508771
B52: ORDER LINE | C52: STYLE NO | E52: DESCRIPTION | J52: HS CODE
B53: 001 | C53: TI12081-010 | E53: FC UTRECHT PERFORMANCE KNIT SUIT | J53: 61109000 | L53: 25 | M53: 15.28 | N53: =M53*L53 -> 382
B54: 002 | C54: TJ12046-072 | E54: FC UTRECHT PERFORMANCE SHORT SLEEVE TEE | J54: 61099020 | L54: 171 | M54: 4.87 | N54: =L54*M54 -> 832.77
B55: 003 | C55: TJ12049-010 | E55: FC UTRECHT PERFORMANCE KNIT SHORT- PKTS | J55: 61034900 | L55: 141 | M55: 6.74 | N55: =L55*M55 -> 950.34
B56: 004 | C56: TJ12050-010 | E56: FC UTRECHT PERFORMANCE MIDLAYER TOP | J56: 61109000 | L56: 126 | M56: 11.08 | N56: =L56*M56 -> 1396.08
B57: 005 | C57: TJ12052-010 | E57: FC UTRECHT PERFORMANCE KNIT PANT- PKTS | J57: 61034900 | L57: 119 | M57: 11.92 | N57: =L57*M57 -> 1418.48
B58: 007 | C58: TM12049-010 | E58: FC UTRECHT PERFORMANCE KNIT SHORT- PKTS | J58: 61034900 | L58: 162 | M58: 7.52 | N58: =L58*M58 -> 1218.24
B59: 008 | C59: TM12050-010 | E59: FC UTRECHT PERFORMANCE MIDLAYER TOP | J59: 61109000 | L59: 134 | M59: 12.33 | N59: =L59*M59 -> 1652.22
B60: 009 | C60: TM12052-010 | E60: FC UTRECHT PERFORMANCE KNIT PANT- PKTS | J60: 61034900 | L60: 124 | M60: 13.27 | N60: =L60*M60 -> 1645.48
B61: 006 | C61: TM12046-072 | E61: FC UTRECHT PERFORMANCE SHORT SLEEVE TEE | J61: 61099020 | L61: 198 | M61: 5.44 | N61: =L61*M61 -> 1077.12
B62: SUB TOTAL | L62: =SUM(L53:L61) -> 1200 | N62: =SUM(N53:N61) -> 10572.73
B64: 3 CARTONS = 76 PIECES OF APPAREL GOODS
B65: PO NO. : WPO12508772
B66: ORDER LINE | C66: STYLE NO | E66: DESCRIPTION | J66: HS CODE
B67: 001 | C67: TI12081-090 | E67: FC UTRECHT PERFORMANCE KNIT SUIT | J67: 61109000 | L67: 25 | M67: 15.25 | N67: =M67*L67 -> 381.25
B68: 002 | C68: TJ12046-090 | E68: FC UTRECHT PERFORMANCE SHORT SLEEVE TEE | J68: 61099020 | L68: 25 | M68: 4.88 | N68: =M68*L68 -> 122
B69: 006 | C69: TM12046-090 | E69: FC UTRECHT PERFORMANCE SHORT SLEEVE TEE | J69: 61099020 | L69: 26 | M69: 5.47 | N69: =M69*L69 -> 142.22
B70: 004 | C70: TJ12050-090 | E70: FC UTRECHT PERFORMANCE MIDLAYER TOP | J70: 61109000 | L70: 25 | M70: 11.09 | N70: =L70*M70 -> 277.25
B71: 005 | C71: TJ12052-090 | E71: FC UTRECHT PERFORMANCE KNIT PANT- PKTS | J71: 61034900 | L71: 25 | M71: 11.92 | N71: =L71*M71 -> 298
B72: 008 | C72: TM12050-090 | E72: FC UTRECHT PERFORMANCE MIDLAYER TOP | J72: 61109000 | L72: 26 | M72: 12.36 | N72: =L72*M72 -> 321.36
B73: 009 | C73: TM12052-090 | E73: FC UTRECHT PERFORMANCE KNIT PANT- PKTS | J73: 61034900 | L73: 26 | M73: 13.3 | N73: =L73*M73 -> 345.8
B74: 003 | C74: TJ12049-090 | E74: FC UTRECHT PERFORMANCE KNIT SHORT- PKTS | J74: 61034900 | L74: 25 | M74: 6.76 | N74: =L74*M74 -> 169
B75: 007 | C75: TM12049-090 | E75: FC UTRECHT PERFORMANCE KNIT SHORT- PKTS | J75: 61034900 | L75: 26 | M75: 7.55 | N75: =L75*M75 -> 196.3
B76: SUB TOTAL | L76: =SUM(L67:L75) -> 229 | N76: =SUM(N67:N75) -> 2253.18
B78: 20 CARTONS = 524 PIECES OF APPAREL GOODS
B79: PO NO. : EPO12508757
B80: ORDER LINE | C80: STYLE NO | E80: DESCRIPTION | J80: HS CODE
B81: 003 | C81: TJ12050-090 | E81: FC UTRECHT PERFORMANCE MIDLAYER TOP | J81: 61109000 | L81: 152 | M81: 11.09 | N81: =L81*M81 -> 1685.68
B82: 005 | C82: TM12050-090 | E82: FC UTRECHT PERFORMANCE MIDLAYER TOP | J82: 61109000 | L82: 300 | M82: 12.36 | N82: =L82*M82 -> 3708
B83: 001 | C83: TF12048-090 | E83: FC UTRECHT PERFORMANCE KNIT SHORT- WO PKTS | J83: 61034900 | L83: 72 | M83: 6.22 | N83: =L83*M83 -> 447.84
B84: SUB TOTAL | L84: =SUM(L81:L83) -> 524 | N84: =SUM(N81:N83) -> 5841.52
B86: GRAND TOTAL | L86: =L48+L62+L76+L84 -> 3711 | N86: =N48+N62+N76+N84 -> 34802.09
B87: Country of Origin | D87: : | E87: INDONESIA
B88: Incoterms | D88: : | E88: FCA SOEKARNO HATTA, JAKARTA AIRPORT, INDONESIA
B89: EORI No. | D89: :
G90: MEAS | H90: ='PL FC Utrecht'!Y425 -> 6.05 | I90: CBM
G91: GROSS WT | H91: ='PL FC Utrecht'!V425 -> 1194.678 | I91: KGS
G92: NET WT | H92: ='PL FC Utrecht'!W425 -> 1033.358 | I92: KGS
G93: PACKING | H93: ='PL FC Utrecht'!R425 -> 116 | I93: CTNS
B94: SAY : | C94: USD THIRTY FOUR THOUSAND EIGHT HUNDRED TWO AND CENTS NINEONLY
B96: Other Remarks & Noted | D96: :
B99: MANUFACTURER | D99: : | E99: PT. MORICH INDO FASHION
E100: JL. Raya Karangjati KM 25
E101: SEMARANG - INDONESIA
E102: PHONE : (0298)523523
E103: FAX : (0298)522095
E104: TAX ID : 1.287.855.9-511.000
E105: POS CODE : 50552
B107: BANK DETAILS
B108: A/C NO. | D108: : | E108: 0029042494
B109: BANK NAME | D109: : | E109: PT. BANK NEGARA INDONESIA (PERSERO)
E110: KANTOR CAB. KARANGAYU | L110: Authorized Signature
E111: SEMARANG
B112: SWIFT CODE | D112: : | E112: BNINIDJAKRU

Sheet PL FC Utrecht
C4: PACKING LIST
A6: Consignee : | C6: Notify Party : | I6: DATE | O6: : | R6: 45810
A7: J. CARTER SPORTING CLUB LIMITED 1 CENTRAL STREET, MANCHESTER, M2 5WR UNITED KINGDOM, | C7: J. CARTER SPORTING CLUB LIMITED 1 CENTRAL STREET, MANCHESTER, M2 5WR UNITED KINGDOM, | I7: INVOICE | O7: : | R7: 0654/INV/2025
I8: L/C NO. | O8: : | R8: IMP750070263
I9: DATE OF ISSUE | O9: : | R9: 45956
I10: HBL / HAWB NO. | O10: :
I11: SHIPPED ON BOARD DATE | O11: :
I12: PORT OF DISCHARGE | O12: : | R12: AMSTERDAM, NL
I13: COUNTRY OF ORIGIN | O13: : | R13: INDONESIA
I14: PORT OF DELIVERY | O14: : | R14: AMSTERDAM, NL
I15: CONTAINER / SIZE / SEAL NO. | O15: :
A17: NAME OF VESSEL / FLIGHT | C17: TBA
A18: PORT OF SHIPMENT | C18: SOEKARNO HATTA, JAKARTA AIRPORT, INDONESIA
A19: MAIN MARK | I19: DESCRIPTION OF GOODS
I20: INTERNAL ID-51808115-E-COMMERCE
I26: PO NO. EPO12508755
A27: STYLE | B27: STYLE DESCRIPTION | C27: OP NO | D27: ORDER | E27: SIZE | O27: C/NO | R27: TOT | S27: TOT | T27: GW | U27: NW | V27: GW | W27: NW | X27: CARTON | Y27: CBM | Z27: POLYBAG
D28: LINE | E28: 2-3Y | F28: 3-4Y | G28: 4-5Y | H28: 5-6Y | I28: 6-7Y | R28: CTN | S28: PCS | T28: CARTON | U28: CARTON | V28: ( Kg ) | W28: ( Kg ) | X28: MEAS | Z28: WEIGHT
A29: TI12081-010 | B29: FC UTRECHT PERFORMANCE KNIT SUIT | C29: 25-02175B-1 | D29: 001 | H29: 24 | O29: 1 | Q29: =O29+R29-1 -> 1 | R29: 1 | S29: =SUM(E29:N29)*R29 -> 24 | T29: =IF(X29="595X289X390",1.46,IF(X29="597X292X191",0.96,IF(X29="560X600X390",2.04,IF(X29="560X400X390",1.84))))+U29 -> 11.54 | U29: =+((E29*0.35)+(F29*0.37)+(G29*0.39)+(H29*0.42)+(I29*0.44)+(J29*0.46)+(K29*0.456)+(L29*0.468)+(M29*0.478)) -> 10.08 | V29: =T29*R29 -> 11.54 | W29: =U29*R29 -> 10.08 | X29: 595X289X390 | Y29: =IF(X29="595X289X390",0.071,IF(X29="597X292X191",0.034,IF(X29="560X600X390",0.132,IF(X29="560X400X390",0.088))))*R29 -> 0.071 | Z29: 0
E30: 3 | G30: 22 | O30: =Q29+1 -> 2 | Q30: =O30+R30-1 -> 2 | R30: 1 | S30: =SUM(E30:N30)*R30 -> 25 | T30: =IF(X30="595X289X390",1.46,IF(X30="597X292X191",0.96,IF(X30="560X600X390",2.04,IF(X30="560X400X390",1.84))))+U30 -> 11.09 | U30: =+((E30*0.35)+(F30*0.37)+(G30*0.39)+(H30*0.42)+(I30*0.44)+(J30*0.46)+(K30*0.456)+(L30*0.468)+(M30*0.478)) -> 9.63 | V30: =T30*R30 -> 11.09 | W30: =U30*R30 -> 9.63 | X30: 595X289X390 | Y30: =IF(X30="595X289X390",0.071,IF(X30="597X292X191",0.034,IF(X30="560X600X390",0.132,IF(X30="560X400X390",0.088))))*R30 -> 0.071 | Z30: 0
F31: 21 | I31: 4 | O31: =Q30+1 -> 3 | Q31: =O31+R31-1 -> 3 | R31: 1 | S31: =SUM(E31:N31)*R31 -> 25 | T31: =IF(X31="595X289X390",1.46,IF(X31="597X292X191",0.96,IF(X31="560X600X390",2.04,IF(X31="560X400X390",1.84))))+U31 -> 10.99 | U31: =+((E31*0.35)+(F31*0.37)+(G31*0.39)+(H31*0.42)+(I31*0.44)+(J31*0.46)+(K31*0.456)+(L31*0.468)+(M31*0.478)) -> 9.53 | V31: =T31*R31 -> 10.99 | W31: =U31*R31 -> 9.53 | X31: 595X289X390 | Y31: =IF(X31="595X289X390",0.071,IF(X31="597X292X191",0.034,IF(X31="560X600X390",0.132,IF(X31="560X400X390",0.088))))*R31 -> 0.071 | Z31: 0
E32: 12 | I32: 14 | O32: =Q31+1 -> 4 | Q32: =O32+R32-1 -> 4 | R32: 1 | S32: =SUM(E32:N32)*R32 -> 26 | T32: =IF(X32="595X289X390",1.46,IF(X32="597X292X191",0.96,IF(X32="560X600X390",2.04,IF(X32="560X400X390",1.84))))+U32 -> 11.82 | U32: =+((E32*0.35)+(F32*0.37)+(G32*0.39)+(H32*0.42)+(I32*0.44)+(J32*0.46)+(K32*0.456)+(L32*0.468)+(M32*0.478)) -> 10.36 | V32: =T32*R32 -> 11.82 | W32: =U32*R32 -> 10.36 | X32: 595X289X390 | Y32: =IF(X32="595X289X390",0.071,IF(X32="597X292X191",0.034,IF(X32="560X600X390",0.132,IF(X32="560X400X390",0.088))))*R32 -> 0.071 | Z32: 0
C33: SUB TOTAL | R33: =SUM(R29:R32) -> 4 | S33: =SUM(S29:S32) -> 100 | T33: =SUM(T29:T32) -> 45.44 | U33: =SUM(U29:U32) -> 39.6 | V33: =SUM(V29:V32) -> 45.44 | W33: =SUM(W29:W32) -> 39.6 | Y33: =SUM(Y29:Y32) -> 0.284 | Z33: =SUM(Z29:Z32) -> 0
C34: TOTAL SHIPPED | E34: 15 | F34: 21 | G34: 22 | H34: 24 | I34: 18 | O34: 100
C35: TOTAL ORDERED | E35: 15 | F35: 21 | G35: 22 | H35: 24 | I35: 18 | O35: 100
C36: SHORTAGE/OVER
C37: PERCENTAGE
A39: STYLE | B39: STYLE DESCRIPTION | C39: OP NO | D39: ORDER | E39: SIZE | O39: C/NO | R39: TOT | S39: TOT | T39: GW | U39: NW | V39: GW | W39: NW | X39: CARTON | Y39: CBM | Z39: POLYBAG
D40: LINE | E40: JXS | F40: JS | G40: JM | H40: JL | I40: JXL | R40: CTN | S40: PCS | T40: CARTON | U40: CARTON | V40: ( Kg ) | W40: ( Kg ) | X40: MEAS | Z40: WEIGHT
A41: TJ12049-010 | B41: FC UTRECHT PERFORMANCE KNIT SHORT- PKTS | C41: 25-02168C-1 | D41: 003 | E41: 10 | F41: 16 | G41: 24 | H41: 26 | I41: 24 | O41: =Q32+1 -> 5 | Q41: =O41+R41-1 -> 5 | R41: 1 | S41: =SUM(E41:N41)*R41 -> 100 | T41: 3.58 | U41: 2.6 | V41: 3.58 | W41: 2.6 | X41: 595X289X390 | Y41: =IF(X41="595X289X390",0.071,IF(X41="597X292X191",0.034,IF(X41="560X600X390",0.132,IF(X41="560X400X390",0.088))))*R41 -> 0.071 | Z41: 0
C43: SUB TOTAL | R43: =SUM(R41) -> 1 | S43: =SUM(S41) -> 100 | T43: 35.66 | U43: 30.76 | V43: 35.66 | W43: 30.76 | Y43: =SUM(Y41) -> 0.071 | Z43: 0
C44: TOTAL SHIPPED | E44: 10 | F44: 16 | G44: 24 | H44: 26 | I44: 24 | O44: =SUM(E44:N44) -> 100
C45: TOTAL ORDERED | E45: 10 | F45: 16 | G45: 24 | H45: 26 | I45: 24 | O45: =SUM(E45:N45) -> 100
C46: SHORTAGE/OVER
C47: PERCENTAGE
A49: STYLE | B49: STYLE DESCRIPTION | C49: OP NO | D49: ORDER | E49: SIZE | O49: C/NO | R49: TOT | S49: TOT | T49: GW | U49: NW | V49: GW | W49: NW | X49: CARTON | Y49: CBM | Z49: POLYBAG
D50: LINE | E50: JXS | F50: JS | G50: JM | H50: JL | I50: JXL | R50: CTN | S50: PCS | T50: CARTON | U50: CARTON | V50: ( Kg ) | W50: ( Kg ) | X50: MEAS | Z50: WEIGHT
A51: TJ12050-010 | B51: FC UTRECHT PERFORMANCE MIDLAYER TOP | C51: 25-02159C-1 | D51: 004 | E51: 18 | O51: =Q41+1 -> 6 | Q51: =O51+R51-1 -> 6 | R51: 1 | S51: =SUM(E51:N51)*R51 -> 18 | T51: 3.5 | U51: 2.52 | V51: 3.5 | W51: 2.52 | X51: 597X292X191 | Y51: =IF(X51="595X289X390",0.071,IF(X51="597X292X191",0.034,IF(X51="560X600X390",0.132,IF(X51="560X400X390",0.088))))*R51 -> 0.034 | Z51: 0
F52: 20 | O52: =Q51+1 -> 7 | Q52: =O52+R52-1 -> 7 | R52: 1 | S52: =SUM(E52:N52)*R52 -> 20 | T52: 5.74 | U52: 4.16 | V52: 5.74 | W52: 4.16 | X52: 597X292X191 | Y52: =IF(X52="595X289X390",0.071,IF(X52="597X292X191",0.034,IF(X52="560X600X390",0.132,IF(X52="560X400X390",0.088))))*R52 -> 0.034 | Z52: 0
G53: 20 | O53: =Q52+1 -> 8 | Q53: =O53+R53-1 -> 8 | R53: 1 | S53: =SUM(E53:N53)*R53 -> 20 | T53: 6.62 | U53: 5.04 | V53: 6.62 | W53: 5.04 | X53: 597X292X191 | Y53: =IF(X53="595X289X390",0.071,IF(X53="597X292X191",0.034,IF(X53="560X600X390",0.132,IF(X53="560X400X390",0.088))))*R53 -> 0.034 | Z53: 0
H54: 20 | O54: =Q53+1 -> 9 | Q54: =O54+R54-1 -> 9 | R54: 1 | S54: =SUM(E54:N54)*R54 -> 20 | T54: 7.98 | U54: 6.4 | V54: 7.98 | W54: 6.4 | X54: 597X292X191 | Y54: =IF(X54="595X289X390",0.071,IF(X54="597X292X191",0.034,IF(X54="560X600X390",0.132,IF(X54="560X400X390",0.088))))*R54 -> 0.034 | Z54: 0
I55: 40 | O55: =Q54+1 -> 10 | Q55: =O55+R55-1 -> 10 | R55: 1 | S55: =SUM(E55:N55)*R55 -> 40 | T55: 7.98 | U55: 6.4 | V55: 7.98 | W55: 6.4 | X55: 595X289X390 | Y55: =IF(X55="595X289X390",0.071,IF(X55="597X292X191",0.034,IF(X55="560X600X390",0.132,IF(X55="560X400X390",0.088))))*R55 -> 0.071 | Z55: 0
F56: 6 | G56: 8 | H56: 12 | I56: 6 | O56: =Q55+1 -> 11 | Q56: =O56+R56-1 -> 11 | R56: 1 | S56: =SUM(E56:N56)*R56 -> 32 | T56: 7.98 | U56: 6.4 | V56: 7.98 | W56: 6.4 | X56: 595X289X390 | Y56: =IF(X56="595X289X390",0.071,IF(X56="597X292X191",0.034,IF(X56="560X600X390",0.132,IF(X56="560X400X390",0.088))))*R56 -> 0.071 | Z56: 0
C57: SUB TOTAL | R57: =SUM(R51:R56) -> 6 | S57: =SUM(S51:S56) -> 150 | T57: 35.54 | U57: 28.24 | V57: 35.54 | W57: 28.24 | Y57: =SUM(Y51:Y56) -> 0.278 | Z57: 0
C58: TOTAL SHIPPED | E58: 18 | F58: 26 | G58: 28 | H58: 32 | I58: 46 | O58: =SUM(E58:N58) -> 150
C59: TOTAL ORDERED | E59: 18 | F59: 26 | G59: 28 | H59: 32 | I59: 46 | O59: =SUM(E59:N59) -> 150
C60: SHORTAGE/OVER
C61: PERCENTAGE
A63: STYLE | B63: STYLE DESCRIPTION | C63: OP NO | D63: ORDER | E63: SIZE | O63: C/NO | R63: TOT | S63: TOT | T63: GW | U63: NW | V63: GW | W63: NW | X63: CARTON | Y63: CBM | Z63: POLYBAG
D64: LINE | E64: JXS | F64: JS | G64: JM | H64: JL | I64: JXL | R64: CTN | S64: PCS | T64: CARTON | U64: CARTON | V64: ( Kg ) | W64: ( Kg ) | X64: MEAS | Z64: WEIGHT
A65: TJ12052-010 | B65: FC UTRECHT PERFORMANCE KNIT PANT- PKTS | C65: 25-02174C-1 | D65: 005 | G65: 18 | O65: =Q56+1 -> 12 | Q65: =O65+R65-1 -> 12 | R65: 1 | S65: =SUM(E65:N65)*R65 -> 18 | T65: 4.62 | U65: 3.64 | V65: 4.62 | W65: 3.64 | X65: 597X292X191 | Y65: =IF(X65="595X289X390",0.071,IF(X65="597X292X191",0.034,IF(X65="560X600X390",0.132,IF(X65="560X400X390",0.088))))*R65 -> 0.034 | Z65: 0
H66: 20 | O66: =Q65+1 -> 13 | Q66: =O66+R66-1 -> 13 | R66: 1 | S66: =SUM(E66:N66)*R66 -> 20 | T66: 5.46 | U66: 4.48 | V66: 5.46 | W66: 4.48 | X66: 597X292X191 | Y66: =IF(X66="595X289X390",0.071,IF(X66="597X292X191",0.034,IF(X66="560X600X390",0.132,IF(X66="560X400X390",0.088))))*R66 -> 0.034 | Z66: 0
I67: 20 | O67: =Q66+1 -> 14 | Q67: =O67+R67-1 -> 14 | R67: 1 | S67: =SUM(E67:N67)*R67 -> 20 | T67: 6.38 | U67: 5.4 | V67: 6.38 | W67: 5.4 | X67: 597X292X191 | Y67: =IF(X67="595X289X390",0.071,IF(X67="597X292X191",0.034,IF(X67="560X600X390",0.132,IF(X67="560X400X390",0.088))))*R67 -> 0.034 | Z67: 0
E68: 14 | F68: 16 | H68: 4 | I68: 8 | O68: =Q67+1 -> 15 | Q68: =O68+R68-1 -> 15 | R68: 1 | S68: =SUM(E68:N68)*R68 -> 42 | T68: 8.66 | U68: 7.68 | V68: 8.66 | W68: 7.68 | X68: 595X289X390 | Y68: =IF(X68="595X289X390",0.071,IF(X68="597X292X191",0.034,IF(X68="560X600X390",0.132,IF(X68="560X400X390",0.088))))*R68 -> 0.071 | Z68: 0
C70: SUB TOTAL | R70: =SUM(R65:R68) -> 4 | S70: =SUM(S65:S68) -> 100 | T70: 35.62 | U70: 30.72 | V70: 35.62 | W70: 30.72 | Y70: =SUM(Y65:Y69) -> 0.173 | Z70: 0
C71: TOTAL SHIPPED | E71: 14 | F71: 16 | G71: 18 | H71: 24 | I71: 28 | O71: =SUM(E71:N71) -> 100
C72: TOTAL ORDERED | E72: 14 | F72: 16 | G72: 18 | H72: 24 | I72: 28 | O72: =SUM(E72:N72) -> 100
C73: SHORTAGE/OVER
C74: PERCENTAGE
A76: STYLE | B76: STYLE DESCRIPTION | C76: OP NO | D76: ORDER | E76: SIZE | O76: C/NO | R76: TOT | S76: TOT | T76: GW | U76: NW | V76: GW | W76: NW | X76: CARTON | Y76: CBM | Z76: POLYBAG
D77: LINE | E77: S | F77: M | G77: L | H77: XL | I77: 2XL | J77: 3XL | K77: 4XL | L77: 5XL | R77: CTN | S77: PCS | T77: CARTON | U77: CARTON | V77: ( Kg ) | W77: ( Kg ) | X77: MEAS | Z77: WEIGHT
A78: TM12049-010 | B78: FC UTRECHT PERFORMANCE KNIT SHORT- PKTS | C78: 25-02166C-1 | D78: 007 | E78: 30 | O78: =Q68+1 -> 16 | Q78: =O78+R78-1 -> 16 | R78: 1 | S78: =SUM(E78:N78)*R78 -> 30 | T78: 17.42 | U78: 15.84 | V78: 17.42 | W78: 15.84 | X78: 595X289X390 | Y78: =IF(X78="595X289X390",0.071,IF(X78="597X292X191",0.034,IF(X78="560X600X390",0.132,IF(X78="560X400X390",0.088))))*R78 -> 0.071 | Z78: 0
F79: 60 | O79: =Q78+1 -> 17 | Q79: =O79+R79-1 -> 17 | R79: 1 | S79: =SUM(E79:N79)*R79 -> 60 | T79: 24.38 | U79: 22.8 | V79: 24.38 | W79: 22.8 | X79: 595X289X390 | Y79: =IF(X79="595X289X390",0.071,IF(X79="597X292X191",0.034,IF(X79="560X600X390",0.132,IF(X79="560X400X390",0.088))))*R79 -> 0.071 | Z79: 0
G80: 30 | O80: =Q79+1 -> 18 | Q80: =O80+R80-1 -> 18 | R80: 1 | S80: =SUM(E80:N80)*R80 -> 30 | T80: 4.78 | U80: 3.8 | V80: 4.78 | W80: 3.8 | X80: 597X292X191 | Y80: =IF(X80="595X289X390",0.071,IF(X80="597X292X191",0.034,IF(X80="560X600X390",0.132,IF(X80="560X400X390",0.088))))*R80 -> 0.034 | Z80: 0
E81: 14 | F81: 10 | G81: 20 | I81: 6 | J81: 6 | O81: =Q80+1 -> 19 | Q81: =O81+R81-1 -> 19 | R81: 1 | S81: =SUM(E81:N81)*R81 -> 56 | T81: 21.58 | U81: 20 | V81: 21.58 | W81: 20 | X81: 595X289X390 | Y81: =IF(X81="595X289X390",0.071,IF(X81="597X292X191",0.034,IF(X81="560X600X390",0.132,IF(X81="560X400X390",0.088))))*R81 -> 0.071 | Z81: 0
H82: 20 | K82: 5 | L82: 5 | O82: =Q81+1 -> 20 | Q82: =O82+R82-1 -> 20 | R82: 1 | S82: =SUM(E82:N82)*R82 -> 30 | T82: 9.38 | U82: 8.4 | V82: 9.38 | W82: 8.4 | X82: 597X292X191 | Y82: =IF(X82="595X289X390",0.071,IF(X82="597X292X191",0.034,IF(X82="560X600X390",0.132,IF(X82="560X400X390",0.088))))*R82 -> 0.034 | Z82: 0
C84: SUB TOTAL | R84: =SUM(R78:R82) -> 5 | S84: =SUM(S78:S82) -> 206 | T84: 91.76 | U84: 81.14 | V84: 91.76 | W84: 81.14 | Y84: =SUM(Y78:Y83) -> 0.281 | Z84: 0
C85: TOTAL SHIPPED | E85: 44 | F85: 70 | G85: 50 | H85: 20 | I85: 6 | J85: 6 | K85: 5 | L85: 5 | O85: =SUM(E85:N85) -> 206
C86: TOTAL ORDERED | E86: 44 | F86: 70 | G86: 50 | H86: 20 | I86: 6 | J86: 6 | K86: 5 | L86: 5 | O86: =SUM(E86:N86) -> 206
C87: SHORTAGE/OVER
C88: PERCENTAGE
A90: STYLE | B90: STYLE DESCRIPTION | C90: OP NO | D90: ORDER | E90: SIZE | O90: C/NO | R90: TOT | S90: TOT | T90: GW | U90: NW | V90: GW | W90: NW | X90: CARTON | Y90: CBM | Z90: POLYBAG
D91: LINE | E91: S | F91: M | G91: L | H91: XL | I91: 2XL | J91: 3XL | K91: 4XL | L91: 5XL | R91: CTN | S91: PCS | T91: CARTON | U91: CARTON | V91: ( Kg ) | W91: ( Kg ) | X91: MEAS | Z91: WEIGHT
A92: TM12050-010 | B92: FC UTRECHT PERFORMANCE MIDLAYER TOP | C92: 25-02154C-1 | D92: 008 | E92: 28 | O92: =Q82+1 -> 21 | Q92: =O92+R92-1 -> 21 | R92: 1 | S92: =SUM(E92:N92)*R92 -> 28 | T92: 13.62 | U92: 12.04 | V92: 13.62 | W92: 12.04 | X92: 595X289X390 | Y92: =IF(X92="595X289X390",0.071,IF(X92="597X292X191",0.034,IF(X92="560X600X390",0.132,IF(X92="560X400X390",0.088))))*R92 -> 0.071 | Z92: 0
F93: 30 | O93: =Q92+1 -> 22 | Q93: =O93+R93-1 -> 22 | R93: 1 | S93: =SUM(E93:N93)*R93 -> 30 | T93: 19.58 | U93: 18 | V93: 19.58 | W93: 18 | X93: 595X289X390 | Y93: =IF(X93="595X289X390",0.071,IF(X93="597X292X191",0.034,IF(X93="560X600X390",0.132,IF(X93="560X400X390",0.088))))*R93 -> 0.071 | Z93: 0
F94: 14 | O94: =Q93+1 -> 23 | Q94: =O94+R94-1 -> 23 | R94: 1 | S94: =SUM(E94:N94)*R94 -> 14 | T94: 7.28 | U94: 6.3 | V94: 7.28 | W94: 6.3 | X94: 597X292X191 | Y94: =IF(X94="595X289X390",0.071,IF(X94="597X292X191",0.034,IF(X94="560X600X390",0.132,IF(X94="560X400X390",0.088))))*R94 -> 0.034 | Z94: 0
G95: 30 | O95: =Q94+1 -> 24 | Q95: =O95+R95-1 -> 25 | R95: 2 | S95: =SUM(E95:N95)*R95 -> 60 | T95: 20.38 | U95: 18.8 | V95: 40.76 | W95: 37.6 | X95: 595X289X390 | Y95: =IF(X95="595X289X390",0.071,IF(X95="597X292X191",0.034,IF(X95="560X600X390",0.132,IF(X95="560X400X390",0.088))))*R95 -> 0.142 | Z95: 0
G96: 14 | O96: =Q95+1 -> 26 | Q96: =O96+R96-1 -> 26 | R96: 1 | S96: =SUM(E96:N96)*R96 -> 14 | T96: 21.18 | U96: 19.6 | V96: 21.18 | W96: 19.6 | X96: 597X292X191 | Y96: =IF(X96="595X289X390",0.071,IF(X96="597X292X191",0.034,IF(X96="560X600X390",0.132,IF(X96="560X400X390",0.088))))*R96 -> 0.034 | Z96: 0
H97: 30 | O97: =Q96+1 -> 27 | Q97: =O97+R97-1 -> 28 | R97: 2 | S97: =SUM(E97:N97)*R97 -> 60 | T97: 10.78 | U97: 9.8 | V97: 10.78 | W97: 9.8 | X97: 595X289X390 | Y97: =IF(X97="595X289X390",0.071,IF(X97="597X292X191",0.034,IF(X97="560X600X390",0.132,IF(X97="560X400X390",0.088))))*R97 -> 0.142 | Z97: 0
I98: 30 | O98: =Q97+1 -> 29 | Q98: =O98+R98-1 -> 29 | R98: 1 | S98: =SUM(E98:N98)*R98 -> 30 | T98: 21.98 | U98: 20.4 | V98: 21.98 | W98: 20.4 | X98: 595X289X390 | Y98: =IF(X98="595X289X390",0.071,IF(X98="597X292X191",0.034,IF(X98="560X600X390",0.132,IF(X98="560X400X390",0.088))))*R98 -> 0.071 | Z98: 0
I99: 14 | O99: =Q98+1 -> 30 | Q99: =O99+R99-1 -> 30 | R99: 1 | S99: =SUM(E99:N99)*R99 -> 14 | T99: 4.04 | U99: 3.06 | V99: 4.04 | W99: 3.06 | X99: 597X292X191 | Y99: =IF(X99="595X289X390",0.071,IF(X99="597X292X191",0.034,IF(X99="560X600X390",0.132,IF(X99="560X400X390",0.088))))*R99 -> 0.034 | Z99: 0
J100: 14 | O100: =Q99+1 -> 31 | Q100: =O100+R100-1 -> 31 | R100: 1 | S100: =SUM(E100:N100)*R100 -> 14 | T100: 8.4 | U100: 7.42 | V100: 8.4 | W100: 7.42 | X100: 597X292X191 | Y100: =IF(X100="595X289X390",0.071,IF(X100="597X292X191",0.034,IF(X100="560X600X390",0.132,IF(X100="560X400X390",0.088))))*R100 -> 0.034 | Z100: 0
F101: 10 | G101: 6 | K101: 10 | O101: =Q100+1 -> 32 | Q101: =O101+R101-1 -> 32 | R101: 1 | S101: =SUM(E101:N101)*R101 -> 26 | T101: 6.48 | U101: 5.5 | V101: 6.48 | W101: 5.5 | X101: 595X289X390 | Y101: =IF(X101="595X289X390",0.071,IF(X101="597X292X191",0.034,IF(X101="560X600X390",0.132,IF(X101="560X400X390",0.088))))*R101 -> 0.071 | Z101: 0
I102: 2 | L102: 8 | O102: =Q101+1 -> 33 | Q102: =O102+R102-1 -> 33 | R102: 1 | S102: =SUM(E102:N102)*R102 -> 10 | T102: 5.54 | U102: 4.56 | V102: 5.54 | W102: 4.56 | X102: 597X292X191 | Y102: =IF(X102="595X289X390",0.071,IF(X102="597X292X191",0.034,IF(X102="560X600X390",0.132,IF(X102="560X400X390",0.088))))*R102 -> 0.034 | Z102: 0
C103: SUB TOTAL | R103: =SUM(R92:R102) -> 13 | S103: =SUM(S92:S102) -> 300 | T103: 159.64 | U103: 144.28 | V103: 159.64 | W103: 144.28 | Y103: =SUM(Y92:Y102) -> 0.738 | Z103: 0
C104: TOTAL SHIPPED | E104: 28 | F104: 54 | G104: 80 | H104: 60 | I104: 46 | J104: 14 | K104: 10 | L104: 8 | O104: =SUM(E104:N104) -> 300
C105: TOTAL ORDERED | E105: 28 | F105: 54 | G105: 80 | H105: 60 | I105: 46 | J105: 14 | K105: 10 | L105: 8 | O105: =SUM(E105:N105) -> 300
C106: SHORTAGE/OVER
C107: PERCENTAGE
A109: STYLE | B109: STYLE DESCRIPTION | C109: OP NO | D109: ORDER | E109: SIZE | O109: C/NO | R109: TOT | S109: TOT | T109: GW | U109: NW | V109: GW | W109: NW | X109: CARTON | Y109: CBM | Z109: POLYBAG
D110: LINE | E110: S | F110: M | G110: L | H110: XL | I110: 2XL | J110: 3XL | K110: 4XL | L110: 5XL | R110: CTN | S110: PCS | T110: CARTON | U110: CARTON | V110: ( Kg ) | W110: ( Kg ) | X110: MEAS | Z110: WEIGHT
A111: TM12052-010 | B111: FC UTRECHT PERFORMANCE KNIT PANT- PKTS | C111: 25-02172C-1 | D111: 009 | E111: 30 | O111: =Q102+1 -> 34 | Q111: =O111+R111-1 -> 34 | R111: 1 | S111: =SUM(E111:N111)*R111 -> 30 | T111: 11.78 | U111: 10.8 | V111: 11.78 | W111: 10.8 | X111: 595X289X390 | Y111: =IF(X111="595X289X390",0.071,IF(X111="597X292X191",0.034,IF(X111="560X600X390",0.132,IF(X111="560X400X390",0.088))))*R111 -> 0.071 | Z111: 0
F112: 30 | O112: =Q111+1 -> 35 | Q112: =O112+R112-1 -> 35 | R112: 1 | S112: =SUM(E112:N112)*R112 -> 30 | T112: 21.34 | U112: 19.76 | V112: 21.34 | W112: 19.76 | X112: 595X289X390 | Y112: =IF(X112="595X289X390",0.071,IF(X112="597X292X191",0.034,IF(X112="560X600X390",0.132,IF(X112="560X400X390",0.088))))*R112 -> 0.071 | Z112: 0
F113: 14 | O113: =Q112+1 -> 36 | Q113: =O113+R113-1 -> 36 | R113: 1 | S113: =SUM(E113:N113)*R113 -> 14 | T113: 24.78 | U113: 23.2 | V113: 24.78 | W113: 23.2 | X113: 597X292X191 | Y113: =IF(X113="595X289X390",0.071,IF(X113="597X292X191",0.034,IF(X113="560X600X390",0.132,IF(X113="560X400X390",0.088))))*R113 -> 0.034 | Z113: 0
G114: 30 | O114: =Q113+1 -> 37 | Q114: =O114+R114-1 -> 37 | R114: 1 | S114: =SUM(E114:N114)*R114 -> 30 | T114: 13.58 | U114: 12.6 | V114: 13.58 | W114: 12.6 | X114: 595X289X390 | Y114: =IF(X114="595X289X390",0.071,IF(X114="597X292X191",0.034,IF(X114="560X600X390",0.132,IF(X114="560X400X390",0.088))))*R114 -> 0.071 | Z114: 0
G115: 28 | O115: =Q114+1 -> 38 | Q115: =O115+R115-1 -> 38 | R115: 1 | S115: =SUM(E115:N115)*R115 -> 28 | T115: 8.02 | U115: 7.04 | V115: 8.02 | W115: 7.04 | X115: 597X292X191 | Y115: =IF(X115="595X289X390",0.071,IF(X115="597X292X191",0.034,IF(X115="560X600X390",0.132,IF(X115="560X400X390",0.088))))*R115 -> 0.034 | Z115: 0
H116: 30 | O116: =Q115+1 -> 39 | Q116: =O116+R116-1 -> 39 | R116: 1 | S116: =SUM(E116:N116)*R116 -> 30 | T116: 8.02 | U116: 7.04 | V116: 8.02 | W116: 7.04 | X116: 595X289X390 | Y116: =IF(X116="595X289X390",0.071,IF(X116="597X292X191",0.034,IF(X116="560X600X390",0.132,IF(X116="560X400X390",0.088))))*R116 -> 0.071 | Z116: 0
I117: 14 | O117: =Q116+1 -> 40 | Q117: =O117+R117-1 -> 40 | R117: 1 | S117: =SUM(E117:N117)*R117 -> 14 | T117: 8.02 | U117: 7.04 | V117: 8.02 | W117: 7.04 | X117: 597X292X191 | Y117: =IF(X117="595X289X390",0.071,IF(X117="597X292X191",0.034,IF(X117="560X600X390",0.132,IF(X117="560X400X390",0.088))))*R117 -> 0.034 | Z117: 0
F118: 8 | I118: 2 | J118: 6 | K118: 5 | L118: 5 | O118: =Q117+1 -> 41 | Q118: =O118+R118-1 -> 41 | R118: 1 | S118: =SUM(E118:N118)*R118 -> 26 | T118: 8.02 | U118: 7.04 | V118: 8.02 | W118: 7.04 | X118: 595X289X390 | Y118: =IF(X118="595X289X390",0.071,IF(X118="597X292X191",0.034,IF(X118="560X600X390",0.132,IF(X118="560X400X390",0.088))))*R118 -> 0.071 | Z118: 0
C120: SUB TOTAL | R120: =SUM(R111:R118) -> 8 | S120: =SUM(S111:S118) -> 202 | T120: 90.1 | U120: 81.06 | V120: 90.1 | W120: 81.06 | Y120: =SUM(Y111:Y119) -> 0.457 | Z120: 0
...

Sheet CLP
A1: CARGO LOADING PLAN
A3: PACKING LIST NO. | C3: : | D3: 0654/INV/2025
A4: HAWB / HBL NO. | C4: :
A5: PORT OF LOADING | C5: : | D5: SOEKARNO HATTA, JAKARTA AIRPORT, INDONESIA
A6: PORT OF DELIVERY | C6: : | D6: AMSTERDAM, NL
A7: VESSEL / CARRIER NO. | C7: :
A8: ON BOARD DATE | C8: :
A9: SHIP MODE | C9: : | D9: AIR
A10: TRUCK / VEHICLE NO. | C10: :
A11: BOOKING REF. | C11: : | D11: CA25000660
A12: STUFFING DATE | C12: :
A15: FACTORY | B15: PO NO. | D15: ORDER LINE | E15: STYLE / COL. NO. | F15: OP NO. | G15: STYLE NAME | H15: HTS CODE | I15: QTY. CTNS. | J15: QTY. PCS | K15: GW | L15: NW | M15: CBM
A16: MIF 2 | B16: EPO12508755 | D16: 1 | E16: TI12081-010 | F16: 25-02175B-1 | G16: FC UTRECHT PERFORMANCE KNIT SUIT | H16: 61109000 | I16: ='PL FC Utrecht'!R33 -> 4 | J16: ='PL FC Utrecht'!S33 -> 100 | K16: ='PL FC Utrecht'!V33 -> 45.44 | L16: ='PL FC Utrecht'!W33 -> 39.6 | M16: ='PL FC Utrecht'!Y33 -> 0.284
A17: MIF 2 | B17: EPO12508755 | D17: 3 | E17: TJ12049-010 | F17: 25-02168C-1 | G17: FC UTRECHT PERFORMANCE KNIT SHORT- PKTS | H17: 61034900 | I17: ='PL FC Utrecht'!R43 -> 1 | J17: ='PL FC Utrecht'!S43 -> 100 | K17: ='PL FC Utrecht'!V43 -> 35.66 | L17: ='PL FC Utrecht'!W43 -> 30.76 | M17: ='PL FC Utrecht'!Y43 -> 0.071
A18: MIF 2 | B18: EPO12508755 | D18: 4 | E18: TJ12050-010 | F18: 25-02159C-1 | G18: FC UTRECHT PERFORMANCE MIDLAYER TOP | H18: 61109000 | I18: ='PL FC Utrecht'!R57 -> 6 | J18: ='PL FC Utrecht'!S57 -> 150 | K18: ='PL FC Utrecht'!V57 -> 35.54 | L18: ='PL FC Utrecht'!W57 -> 28.24 | M18: ='PL FC Utrecht'!Y57 -> 0.278
A19: MIF 2 | B19: EPO12508755 | D19: 5 | E19: TJ12052-010 | F19: 25-02174C-1 | G19: FC UTRECHT PERFORMANCE KNIT PANT- PKTS | H19: 61034900 | I19: ='PL FC Utrecht'!R70 -> 4 | J19: ='PL FC Utrecht'!S70 -> 100 | K19: ='PL FC Utrecht'!V70 -> 35.62 | L19: ='PL FC Utrecht'!W70 -> 30.72 | M19: ='PL FC Utrecht'!Y70 -> 0.173
A20: MIF 2 | B20: EPO12508755 | D20: 7 | E20: TM12049-010 | F20: 25-02166C-1 | G20: FC UTRECHT PERFORMANCE KNIT SHORT- PKTS | H20: 61034900 | I20: ='PL FC Utrecht'!R84 -> 5 | J20: ='PL FC Utrecht'!S84 -> 206 | K20: ='PL FC Utrecht'!V84 -> 91.76 | L20: ='PL FC Utrecht'!W84 -> 81.14 | M20: ='PL FC Utrecht'!Y84 -> 0.281
A21: MIF 2 | B21: EPO12508755 | D21: 8 | E21: TM12050-010 | F21: 25-02154C-1 | G21: FC UTRECHT PERFORMANCE MIDLAYER TOP | H21: 61109000 | I21: ='PL FC Utrecht'!R103 -> 13 | J21: ='PL FC Utrecht'!S103 -> 300 | K21: ='PL FC Utrecht'!V103 -> 159.64 | L21: ='PL FC Utrecht'!W103 -> 144.28 | M21: ='PL FC Utrecht'!Y103 -> 0.738
A22: MIF 2 | B22: EPO12508755 | D22: 9 | E22: TM12052-010 | F22: 25-02172C-1 | G22: FC UTRECHT PERFORMANCE KNIT PANT- PKTS | H22: 61034900 | I22: ='PL FC Utrecht'!R120 -> 8 | J22: ='PL FC Utrecht'!S120 -> 202 | K22: ='PL FC Utrecht'!V120 -> 90.1 | L22: ='PL FC Utrecht'!W120 -> 81.06 | M22: ='PL FC Utrecht'!Y120 -> 0.457
A23: MIF 2 | B23: EPO12508755 | D23: 2 | E23: TJ12046-072 | F23: 25-02151B-1 | G23: FC UTRECHT PERFORMANCE SHORT SLEEVE TEE | H23: 61099020 | I23: ='PL FC Utrecht'!R131 -> 3 | J23: ='PL FC Utrecht'!S131 -> 200 | K23: ='PL FC Utrecht'!V131 -> 10.76 | L23: ='PL FC Utrecht'!W131 -> 7.82 | M23: ='PL FC Utrecht'!Y131 -> 0.139
A24: MIF 2 | B24: EPO12508755 | D24: 6 | E24: TM12046-072 | F24: 25-02146C-1 | G24: FC UTRECHT PERFORMANCE SHORT SLEEVE TEE | H24: 61099020 | I24: ='PL FC Utrecht'!R147 -> 8 | J24: ='PL FC Utrecht'!S147 -> 400 | K24: ='PL FC Utrecht'!V147 -> 71.3 | L24: ='PL FC Utrecht'!W147 -> 61.06 | M24: ='PL FC Utrecht'!Y147 -> 0.42
A25: MIF 2 | B25: WPO12508771 | D25: 1 | E25: TI12081-010 | F25: 25-02175B-2 | G25: FC UTRECHT PERFORMANCE KNIT SUIT | H25: 61109000 | I25: ='PL FC Utrecht'!R217 -> 1 | J25: ='PL FC Utrecht'!S217 -> 25 | K25: ='PL FC Utrecht'!V217 -> 11.69 | L25: ='PL FC Utrecht'!W217 -> 9.85 | M25: ='PL FC Utrecht'!Y217 -> 0.088
A26: MIF 2 | B26: WPO12508771 | D26: 2 | E26: TJ12046-072 | F26: 25-02151B-3 | G26: FC UTRECHT PERFORMANCE SHORT SLEEVE TEE | H26: 61099020 | I26: ='PL FC Utrecht'!R228 -> 3 | J26: ='PL FC Utrecht'!S228 -> 171 | K26: ='PL FC Utrecht'!V228 -> 26.31 | L26: ='PL FC Utrecht'!W228 -> 20.21 | M26: ='PL FC Utrecht'!Y228 -> 0.139
A27: MIF 2 | B27: WPO12508771 | D27: 3 | E27: TJ12049-010 | F27: 25-02168C-2 | G27: FC UTRECHT PERFORMANCE KNIT SHORT- PKTS | H27: 61034900 | I27: ='PL FC Utrecht'!R238 -> 2 | J27: ='PL FC Utrecht'!S238 -> 141 | K27: ='PL FC Utrecht'!V238 -> 50.3 | L27: ='PL FC Utrecht'!W238 -> 44.8 | M27: ='PL FC Utrecht'!Y238 -> 0.105
A28: MIF 2 | B28: WPO12508771 | D28: 4 | E28: TJ12050-010 | F28: 25-02159C-3 | G28: FC UTRECHT PERFORMANCE MIDLAYER TOP | H28: 61109000 | I28: ='PL FC Utrecht'!R250 -> 4 | J28: ='PL FC Utrecht'!S250 -> 126 | K28: ='PL FC Utrecht'!V250 -> 31.28 | L28: ='PL FC Utrecht'!W250 -> 24.58 | M28: ='PL FC Utrecht'!Y250 -> 0.247
A29: MIF 2 | B29: WPO12508771 | D29: 5 | E29: TJ12052-010 | F29: 25-02174C-3 | G29: FC UTRECHT PERFORMANCE KNIT PANT- PKTS | H29: 61034900 | I29: ='PL FC Utrecht'!R262 -> 4 | J29: ='PL FC Utrecht'!S262 -> 119 | K29: ='PL FC Utrecht'!V262 -> 42.34 | L29: ='PL FC Utrecht'!W262 -> 37.44 | M29: ='PL FC Utrecht'!Y262 -> 0.21
A30: MIF 2 | B30: WPO12508771 | D30: 7 | E30: TM12049-010 | F30: 25-02166C-3 | G30: FC UTRECHT PERFORMANCE KNIT SHORT- PKTS | H30: 61034900 | I30: ='PL FC Utrecht'!R275 -> 5 | J30: ='PL FC Utrecht'!S275 -> 162 | K30: ='PL FC Utrecht'!V275 -> 68.76 | L30: ='PL FC Utrecht'!W275 -> 60.7 | M30: ='PL FC Utrecht'!Y275 -> 0.207
A31: MIF 2 | B31: WPO12508771 | D31: 8 | E31: TM12050-010 | F31: 25-02154C-5 | G31: FC UTRECHT PERFORMANCE MIDLAYER TOP | H31: 61109000 | I31: ='PL FC Utrecht'!R288 -> 5 | J31: ='PL FC Utrecht'!S288 -> 134 | K31: ='PL FC Utrecht'!V288 -> 68.57 | L31: ='PL FC Utrecht'!W288 -> 58.93 | M31: ='PL FC Utrecht'!Y288 -> 0.318
A32: MIF 2 | B32: WPO12508771 | D32: 9 | E32: TM12052-010 | F32: 25-02172C-4 | G32: FC UTRECHT PERFORMANCE KNIT PANT- PKTS | H32: 61034900 | I32: ='PL FC Utrecht'!R302 -> 6 | J32: ='PL FC Utrecht'!S302 -> 124 | K32: ='PL FC Utrecht'!V302 -> 55 | L32: ='PL FC Utrecht'!W302 -> 46.94 | M32: ='PL FC Utrecht'!Y302 -> 0.315
A33: MIF 2 | B33: WPO12508771 | D33: 6 | E33: TM12046-072 | F33: 25-02146C-5 | G33: FC UTRECHT PERFORMANCE SHORT SLEEVE TEE | H33: 61099020 | I33: ='PL FC Utrecht'!R315 -> 5 | J33: ='PL FC Utrecht'!S315 -> 198 | K33: ='PL FC Utrecht'!V315 -> 26.31 | L33: ='PL FC Utrecht'!W315 -> 20.21 | M33: ='PL FC Utrecht'!Y315 -> 0.207
A34: MIF 2 | B34: WPO12508772 | D34: 1 | E34: TI12081-090 | F34: 25-02175B-3 | G34: FC UTRECHT PERFORMANCE KNIT SUIT | H34: 61109000 | I34: ='PL FC Utrecht'!R336 -> 1 | J34: ='PL FC Utrecht'!S336 -> 25 | K34: ='PL FC Utrecht'!V336 -> 11.69 | L34: ='PL FC Utrecht'!W336 -> 9.85 | M34: ='PL FC Utrecht'!Y336 -> 0.088
A35: MIF 2 | B35: WPO12508772 | D35: 2 | E35: TJ12046-090 | F35: 25-02151B-4 | G35: FC UTRECHT PERFORMANCE SHORT SLEEVE TEE | H35: 61099020 | I35: ='PL FC Utrecht'!R346 -> 1 | J35: ='PL FC Utrecht'!S346 -> 25 | K35: ='PL FC Utrecht'!V346 -> 5.91 | L35: ='PL FC Utrecht'!W346 -> 4.95 | M35: ='PL FC Utrecht'!Y346 -> 0.034
A36: MIF 2 | B36: WPO12508772 | D36: 6 | E36: TM12046-090 | F36: 25-02146C-6 | G36: FC UTRECHT PERFORMANCE SHORT SLEEVE TEE | H36: 61099020 | I36: ='PL FC Utrecht'!R356 -> 1 | J36: ='PL FC Utrecht'!S356 -> 26 | K36: ='PL FC Utrecht'!V356 -> 6.098 | L36: ='PL FC Utrecht'!W356 -> 5.138 | M36: ='PL FC Utrecht'!Y356 -> 0.034
A37: MIF 2 | B37: WPO12508772 | D37: 4 | E37: TJ12050-090 | F37: 25-02159C-4 | G37: FC UTRECHT PERFORMANCE MIDLAYER TOP | H37: 61109000 | I37: ='PL FC Utrecht'!R366 -> 1 | J37: ='PL FC Utrecht'!S366 -> 25 | K37: ='PL FC Utrecht'!V366 -> 1.12 | L37: ='PL FC Utrecht'!W366 -> 0.14 | M37: ='PL FC Utrecht'!Y366 -> 0.034
A38: MIF 2 | B38: WPO12508772 | D38: 5 | E38: TJ12052-090 | F38: 25-02174C-4 | G38: FC UTRECHT PERFORMANCE KNIT PANT- PKTS | H38: 61099020 | I38: ='PL FC Utrecht'!R376 -> 1 | J38: ='PL FC Utrecht'!S376 -> 25 | K38: ='PL FC Utrecht'!V376 -> 2.28 | L38: ='PL FC Utrecht'!W376 -> 1.3 | M38: ='PL FC Utrecht'!Y376 -> 0.034
A39: MIF 2 | B39: WPO12508772 | D39: 8 | E39: TM12050-090 | F39: 25-02154C-6 | G39: FC UTRECHT PERFORMANCE MIDLAYER TOP | H39: 61034900 | I39: ='PL FC Utrecht'!R386 -> 1 | J39: ='PL FC Utrecht'!S386 -> 26 | K39: ='PL FC Utrecht'!V386 -> 2.27 | L39: ='PL FC Utrecht'!W386 -> 1.29 | M39: ='PL FC Utrecht'!Y386 -> 0.034
A40: MIF 2 | B40: WPO12508772 | D40: 9 | E40: TM12052-090 | F40: 25-02172C-5 | G40: FC UTRECHT PERFORMANCE KNIT PANT- PKTS | H40: 61099020 | I40: ='PL FC Utrecht'!R396 -> 1 | J40: ='PL FC Utrecht'!S396 -> 26 | K40: ='PL FC Utrecht'!V396 -> 2.06 | L40: ='PL FC Utrecht'!W396 -> 1.08 | M40: ='PL FC Utrecht'!Y396 -> 0.034
A41: MIF 2 | B41: WPO12508772 | D41: 3 | E41: TJ12049-090 | F41: 25-02168C-3 | G41: FC UTRECHT PERFORMANCE KNIT SHORT- PKTS | H41: 61034900 | I41: ='PL FC Utrecht'!R406 -> 1 | J41: ='PL FC Utrecht'!S406 -> 25 | K41: ='PL FC Utrecht'!V406 -> 2.28 | L41: ='PL FC Utrecht'!W406 -> 1.3 | M41: ='PL FC Utrecht'!Y406 -> 0.034
A42: MIF 2 | B42: WPO12508772 | D42: 7 | E42: TM12049-090 | F42: 25-02166C-4 | G42: FC UTRECHT PERFORMANCE KNIT SHORT- PKTS | H42: 61034900 | I42: ='PL FC Utrecht'!R416 -> 1 | J42: ='PL FC Utrecht'!S416 -> 26 | K42: ='PL FC Utrecht'!V416 -> 2.06 | L42: ='PL FC Utrecht'!W416 -> 1.08 | M42: ='PL FC Utrecht'!Y416 -> 0.034
A43: MIF 2 | B43: EPO12508757 | D43: 3 | E43: TJ12050-090 | F43: 25-02159C-2 | G43: FC UTRECHT PERFORMANCE MIDLAYER TOP | H43: 61109000 | I43: ='PL FC Utrecht'!R170 -> 6 | J43: ='PL FC Utrecht'!S170 -> 152 | K43: ='PL FC Utrecht'!V170 -> 35.98 | L43: ='PL FC Utrecht'!W170 -> 28.68 | M43: ='PL FC Utrecht'!Y170 -> 0.241
A44: MIF 2 | B44: EPO12508757 | D44: 5 | E44: TM12050-090 | F44: 25-02154C-2 | G44: FC UTRECHT PERFORMANCE MIDLAYER TOP | H44: 61109000 | I44: ='PL FC Utrecht'!R190 -> 13 | J44: ='PL FC Utrecht'!S190 -> 300 | K44: ='PL FC Utrecht'!V190 -> 160.17 | L44: ='PL FC Utrecht'!W190 -> 144.81 | M44: ='PL FC Utrecht'!Y190 -> 0.738
A45: MIF 2 | B45: EPO12508757 | D45: 1 | E45: TF12048-090 | F45: 25-02164B-1 | G45: FC UTRECHT PERFORMANCE KNIT SHORT- WO PKTS | H45: 61034900 | I45: ='PL FC Utrecht'!R200 -> 1 | J45: ='PL FC Utrecht'!S200 -> 72 | K45: ='PL FC Utrecht'!V200 -> 6.38 | L45: ='PL FC Utrecht'!W200 -> 5.4 | M45: ='PL FC Utrecht'!Y200 -> 0.034
G47: TOTAL | I47: =SUM(I16:I46) -> 116 | J47: =SUM(J16:J46) -> 3711 | K47: =SUM(K16:K46) -> 1194.678 | L47: =SUM(L16:L46) -> 1033.358 | M47: =SUM(M16:M46) -> 6.05
